payload/__init__.py
payload_sdk-0.0.1.dist-info/LICENSE
payload_sdk-0.0.1.dist-info/METADATA
payload_sdk-0.0.1.dist-info/WHEEL
payload_sdk-0.0.1.dist-info/RECORD
