Metadata-Version: 2.1
Name: payload-sdk
Version: 0.0.1
Summary: Configurable logging package with modern standards and customizability.
License: MIT
Author: Coggl
Requires-Python: >=3.8,<4.0
Classifier: License :: OSI Approved :: MIT License
Classifier: Programming Language :: Python :: 3
Classifier: Programming Language :: Python :: 3.8
Classifier: Programming Language :: Python :: 3.9
Classifier: Programming Language :: Python :: 3.10
Classifier: Programming Language :: Python :: 3.11
Requires-Dist: pyyaml (>=6.0.1,<7.0.0)
